rst_package_refs/__init__.py
rst_package_refs/__main__.py
rst_package_refs/core.py
rst_package_refs/sphinx.py
rst_package_refs/registry/__init__.py
rst_package_refs/registry/npm.py
rst_package_refs/registry/pypi.py
rst_package_refs-0.1.0.dist-info/METADATA
rst_package_refs-0.1.0.dist-info/WHEEL
rst_package_refs-0.1.0.dist-info/licenses/LICENSE
rst_package_refs-0.1.0.dist-info/RECORD
