Metadata-Version: 2.1
Name: rst-package-refs
Version: 0.1.0
Summary: reStrucuturedText's custom roles and role builder kit for package registries of any languages.
Project-URL: Home, https://github.com/attakei/rst-multi-ref
Project-URL: Repository, https://github.com/attakei/rst-multi-ref
Author-email: Kazuya Takei <myself@attakei.net>
License-File: LICENSE
Classifier: Development Status :: 3 - Alpha
Classifier: Framework :: Sphinx
Classifier: Intended Audience :: Developers
Classifier: License :: OSI Approved :: Apache Software License
Classifier: Operating System :: OS Independent
Classifier: Programming Language :: Python
Classifier: Programming Language :: Python :: 3
Classifier: Programming Language :: Python :: 3 :: Only
Classifier: Programming Language :: Python :: 3.9
Classifier: Programming Language :: Python :: 3.10
Classifier: Programming Language :: Python :: 3.11
Classifier: Programming Language :: Python :: 3.12
Classifier: Topic :: Documentation :: Sphinx
Classifier: Topic :: Software Development
Classifier: Topic :: Software Development :: Documentation
Classifier: Topic :: Text Processing :: Markup :: reStructuredText
Requires-Python: >=3.9
Requires-Dist: docutils
Provides-Extra: sphinx
Requires-Dist: sphinx; extra == 'sphinx'
